kubejyg/__init__.py
kubejyg/kubejyg.py
kubejyg-0.3.17.dist-info/METADATA
kubejyg-0.3.17.dist-info/WHEEL
kubejyg-0.3.17.dist-info/entry_points.txt
kubejyg-0.3.17.dist-info/licenses/LICENSE
kubejyg-0.3.17.dist-info/RECORD
