Metadata-Version: 2.4
Name: kubejyg
Version: 0.3.17
Summary: kubejyg: Kubernetes Resource Extraction with Namespace Grouping built for filtering with jq, yq and grep.
Project-URL: Homepage, https://github.com/gpetrousov/kubejyg
Project-URL: Issues, https://github.com/gpetrousov/kubejyg/issues
Author-email: Ioannis Petrousov <contact@petrousoft.com>
License-File: LICENSE
Classifier: License :: OSI Approved :: GNU General Public License v3 (GPLv3)
Classifier: Operating System :: OS Independent
Classifier: Programming Language :: Python :: 3
Requires-Python: >=3.8
Requires-Dist: kubernetes>=27.0.0
